okerrclient/__init__.py
okerrclient/api.py
okerrclient/exceptions.py
okerrclient/fs.py
okerrclient/listcmd.py
okerrclient/network.py
okerrclient/pidfile.py
okerrclient/run.py
okerrclient/stdin.py
okerrclient/taskproc.py
okerrclient/taskseq.py
okerrclient/utils.py
okerrclient/pyping/__init__.py
okerrclient/pyping/core.py
okerrclient-2.0.164.data/data/okerrclient/conf/okerrclient.conf
okerrclient-2.0.164.data/data/okerrclient/init.d/okerrclient
okerrclient-2.0.164.data/data/okerrclient/systemd/okerrclient.service
okerrclient-2.0.164.data/scripts/okerrclient
okerrclient-2.0.164.dist-info/METADATA
okerrclient-2.0.164.dist-info/WHEEL
okerrclient-2.0.164.dist-info/top_level.txt
okerrclient-2.0.164.dist-info/RECORD
