Metadata-Version: 2.1
Name: okerrclient
Version: 2.0.164
Summary: client for okerr cloud monitoring system
Home-page: https://github.com/yaroslaff/okerr-dev
Author: Yaroslav Polyakov
Author-email: xenon@sysattack.com
License: MIT
Platform: UNKNOWN
Requires-Dist: configargparse
Requires-Dist: evalidate
Requires-Dist: fasteners
Requires-Dist: okerrupdate (>=1.1.17)
Requires-Dist: psutil
Requires-Dist: python-daemon
Requires-Dist: requests
Requires-Dist: six
